[{"place_id": 401704787, "licence": "Data \u00a9 OpenStreetMap contributors, ODbL 1.0. http://osm.org/copyright", "osm_type": "relation", "osm_id": 1977949, "lat": "43.6331438", "lon": "3.8795261", "class": "boundary", "type": "administrative", "place_rank": 22, "importance": 0.13340745479514762, "addresstype": "neighbourhood", "name": "Aiguelongue", "display_name": "Aiguelongue, H\u00f4pitaux-Facult\u00e9s, Montpellier, H\u00e9rault, Occitania, Metropolitan France, France", "boundingbox": ["43.6236469", "43.6493160", "3.8684399", "3.8963911"]}]